Metadata-Version: 2.4
Name: unsloth
Version: 2026.1.2
Summary: 2-5X faster training, reinforcement learning & finetuning
Author: Unsloth AI team
Author-email: info@unsloth.ai
Maintainer-email: Daniel Han <danielhanchen@gmail.com>, Michael Han <info@unsloth.ai>
License-Expression: Apache-2.0
Project-URL: homepage, http://www.unsloth.ai
Project-URL: documentation, https://github.com/unslothai/unsloth
Project-URL: repository, https://github.com/unslothai/unsloth
Keywords: ai,llm,reinforcement learning,machine learning,artificial intelligence,pytorch
Classifier: Programming Language :: Python
Classifier: Environment :: GPU
Classifier: Environment :: GPU :: NVIDIA CUDA
Classifier: Topic :: Scientific/Engineering :: Artificial Intelligence
Requires-Python: <3.14,>=3.9
License-File: LICENSE
Requires-Dist: unsloth_zoo>=2026.1.2
Requires-Dist: wheel>=0.42.0
Requires-Dist: packaging
Requires-Dist: torch>=2.4.0
Requires-Dist: torchvision
Requires-Dist: numpy
Requires-Dist: tqdm
Requires-Dist: psutil
Requires-Dist: tyro
Requires-Dist: protobuf
Requires-Dist: xformers>=0.0.27.post2; ("linux" in sys_platform or sys_platform == "win32") and (platform_machine == "AMD64" or platform_machine == "x86_64")
Requires-Dist: bitsandbytes!=0.46.0,!=0.48.0,>=0.45.5
Requires-Dist: triton>=3.0.0; "linux" in sys_platform
Requires-Dist: triton-windows; sys_platform == "win32" and (platform_machine == "AMD64" or platform_machine == "x86_64")
Requires-Dist: sentencepiece>=0.2.0
Requires-Dist: datasets!=4.0.*,!=4.1.0,<4.4.0,>=3.4.1
Requires-Dist: accelerate>=0.34.1
Requires-Dist: peft!=0.11.0,>=0.7.1
Requires-Dist: huggingface_hub>=0.34.0
Requires-Dist: hf_transfer
Requires-Dist: diffusers
Requires-Dist: transformers!=4.52.0,!=4.52.1,!=4.52.2,!=4.52.3,!=4.53.0,!=4.54.0,!=4.55.0,!=4.55.1,!=4.57.0,<=4.57.3,>=4.51.3
Requires-Dist: trl!=0.19.0,<=0.24.0,>=0.18.2
Provides-Extra: huggingface
Requires-Dist: unsloth_zoo>=2026.1.2; extra == "huggingface"
Requires-Dist: wheel>=0.42.0; extra == "huggingface"
Requires-Dist: packaging; extra == "huggingface"
Requires-Dist: torchvision; extra == "huggingface"
Requires-Dist: numpy; extra == "huggingface"
Requires-Dist: tqdm; extra == "huggingface"
Requires-Dist: psutil; extra == "huggingface"
Requires-Dist: tyro; extra == "huggingface"
Requires-Dist: protobuf; extra == "huggingface"
Requires-Dist: sentencepiece>=0.2.0; extra == "huggingface"
Requires-Dist: datasets!=4.0.*,!=4.1.0,<4.4.0,>=3.4.1; extra == "huggingface"
Requires-Dist: accelerate>=0.34.1; extra == "huggingface"
Requires-Dist: peft!=0.11.0,>=0.7.1; extra == "huggingface"
Requires-Dist: huggingface_hub>=0.34.0; extra == "huggingface"
Requires-Dist: hf_transfer; extra == "huggingface"
Requires-Dist: diffusers; extra == "huggingface"
Requires-Dist: transformers!=4.52.0,!=4.52.1,!=4.52.2,!=4.52.3,!=4.53.0,!=4.54.0,!=4.55.0,!=4.55.1,!=4.57.0,<=4.57.3,>=4.51.3; extra == "huggingface"
Requires-Dist: trl!=0.19.0,<=0.24.0,>=0.18.2; extra == "huggingface"
Provides-Extra: base
Requires-Dist: unsloth[huggingface]; extra == "base"
Provides-Extra: cu118only
Requires-Dist: xformers==0.0.22.post7; (("linux" in sys_platform or sys_platform == "win32") and (platform_machine == "AMD64" or platform_machine == "x86_64")) and extra == "cu118only"
Provides-Extra: cu121only
Requires-Dist: xformers==0.0.22.post7; (("linux" in sys_platform or sys_platform == "win32") and (platform_machine == "AMD64" or platform_machine == "x86_64")) and extra == "cu121only"
Provides-Extra: cu118onlytorch211
Requires-Dist: xformers==0.0.23; (("linux" in sys_platform or sys_platform == "win32") and (platform_machine == "AMD64" or platform_machine == "x86_64")) and extra == "cu118onlytorch211"
Provides-Extra: cu121onlytorch211
Requires-Dist: xformers==0.0.23; (("linux" in sys_platform or sys_platform == "win32") and (platform_machine == "AMD64" or platform_machine == "x86_64")) and extra == "cu121onlytorch211"
Provides-Extra: cu118onlytorch212
Requires-Dist: xformers==0.0.23.post1; (("linux" in sys_platform or sys_platform == "win32") and (platform_machine == "AMD64" or platform_machine == "x86_64")) and extra == "cu118onlytorch212"
Provides-Extra: cu121onlytorch212
Requires-Dist: xformers==0.0.23.post1; (("linux" in sys_platform or sys_platform == "win32") and (platform_machine == "AMD64" or platform_machine == "x86_64")) and extra == "cu121onlytorch212"
Provides-Extra: cu118onlytorch220
Requires-Dist: xformers==0.0.24; (("linux" in sys_platform or sys_platform == "win32") and (platform_machine == "AMD64" or platform_machine == "x86_64")) and extra == "cu118onlytorch220"
Provides-Extra: cu121onlytorch220
Requires-Dist: xformers==0.0.24; (("linux" in sys_platform or sys_platform == "win32") and (platform_machine == "AMD64" or platform_machine == "x86_64")) and extra == "cu121onlytorch220"
Provides-Extra: cu118onlytorch230
Requires-Dist: xformers==0.0.27; (("linux" in sys_platform or sys_platform == "win32") and (platform_machine == "AMD64" or platform_machine == "x86_64")) and extra == "cu118onlytorch230"
Provides-Extra: cu121onlytorch230
Requires-Dist: xformers==0.0.27; (("linux" in sys_platform or sys_platform == "win32") and (platform_machine == "AMD64" or platform_machine == "x86_64")) and extra == "cu121onlytorch230"
Provides-Extra: cu118onlytorch240
Requires-Dist: xformers==0.0.27.post2; (("linux" in sys_platform or sys_platform == "win32") and (platform_machine == "AMD64" or platform_machine == "x86_64")) and extra == "cu118onlytorch240"
Provides-Extra: cu121onlytorch240
Requires-Dist: xformers==0.0.27.post2; (("linux" in sys_platform or sys_platform == "win32") and (platform_machine == "AMD64" or platform_machine == "x86_64")) and extra == "cu121onlytorch240"
Provides-Extra: cu118onlytorch250
Requires-Dist: xformers==0.0.28.post2; (("linux" in sys_platform or sys_platform == "win32") and (platform_machine == "AMD64" or platform_machine == "x86_64")) and extra == "cu118onlytorch250"
Provides-Extra: cu121onlytorch250
Requires-Dist: xformers==0.0.28.post2; (("linux" in sys_platform or sys_platform == "win32") and (platform_machine == "AMD64" or platform_machine == "x86_64")) and extra == "cu121onlytorch250"
Provides-Extra: cu124onlytorch250
Requires-Dist: xformers==0.0.28.post2; (("linux" in sys_platform or sys_platform == "win32") and (platform_machine == "AMD64" or platform_machine == "x86_64")) and extra == "cu124onlytorch250"
Provides-Extra: cu118onlytorch251
Requires-Dist: xformers==0.0.29.post1; (("linux" in sys_platform or sys_platform == "win32") and (platform_machine == "AMD64" or platform_machine == "x86_64")) and extra == "cu118onlytorch251"
Provides-Extra: cu121onlytorch251
Requires-Dist: xformers==0.0.29.post1; (("linux" in sys_platform or sys_platform == "win32") and (platform_machine == "AMD64" or platform_machine == "x86_64")) and extra == "cu121onlytorch251"
Provides-Extra: cu124onlytorch251
Requires-Dist: xformers==0.0.29.post1; (("linux" in sys_platform or sys_platform == "win32") and (platform_machine == "AMD64" or platform_machine == "x86_64")) and extra == "cu124onlytorch251"
Provides-Extra: cu118onlytorch260
Requires-Dist: xformers==0.0.29.post3; (("linux" in sys_platform or sys_platform == "win32") and (platform_machine == "AMD64" or platform_machine == "x86_64")) and extra == "cu118onlytorch260"
Provides-Extra: cu124onlytorch260
Requires-Dist: xformers==0.0.29.post3; (("linux" in sys_platform or sys_platform == "win32") and (platform_machine == "AMD64" or platform_machine == "x86_64")) and extra == "cu124onlytorch260"
Provides-Extra: cu126onlytorch260
Requires-Dist: xformers==0.0.29.post3; (("linux" in sys_platform or sys_platform == "win32") and (platform_machine == "AMD64" or platform_machine == "x86_64")) and extra == "cu126onlytorch260"
Provides-Extra: cu118onlytorch270
Requires-Dist: xformers==0.0.30; (("linux" in sys_platform or sys_platform == "win32") and (platform_machine == "AMD64" or platform_machine == "x86_64")) and extra == "cu118onlytorch270"
Provides-Extra: cu126onlytorch270
Requires-Dist: xformers==0.0.30; (("linux" in sys_platform or sys_platform == "win32") and (platform_machine == "AMD64" or platform_machine == "x86_64")) and extra == "cu126onlytorch270"
Provides-Extra: cu128onlytorch270
Requires-Dist: xformers==0.0.30; (("linux" in sys_platform or sys_platform == "win32") and (platform_machine == "AMD64" or platform_machine == "x86_64")) and extra == "cu128onlytorch270"
Provides-Extra: cu118onlytorch271
Requires-Dist: xformers==0.0.31.post1; (("linux" in sys_platform or sys_platform == "win32") and (platform_machine == "AMD64" or platform_machine == "x86_64")) and extra == "cu118onlytorch271"
Provides-Extra: cu126onlytorch271
Requires-Dist: xformers==0.0.31.post1; (("linux" in sys_platform or sys_platform == "win32") and (platform_machine == "AMD64" or platform_machine == "x86_64")) and extra == "cu126onlytorch271"
Provides-Extra: cu128onlytorch271
Requires-Dist: xformers==0.0.31.post1; (("linux" in sys_platform or sys_platform == "win32") and (platform_machine == "AMD64" or platform_machine == "x86_64")) and extra == "cu128onlytorch271"
Provides-Extra: cu118onlytorch280
Requires-Dist: xformers==0.0.32.post2; (("linux" in sys_platform or sys_platform == "win32") and (platform_machine == "AMD64" or platform_machine == "x86_64")) and extra == "cu118onlytorch280"
Provides-Extra: cu126onlytorch280
Requires-Dist: xformers==0.0.32.post2; (("linux" in sys_platform or sys_platform == "win32") and (platform_machine == "AMD64" or platform_machine == "x86_64")) and extra == "cu126onlytorch280"
Provides-Extra: cu128onlytorch280
Requires-Dist: xformers==0.0.32.post2; (("linux" in sys_platform or sys_platform == "win32") and (platform_machine == "AMD64" or platform_machine == "x86_64")) and extra == "cu128onlytorch280"
Provides-Extra: cu130onlytorch280
Provides-Extra: cu126onlytorch290
Requires-Dist: xformers==0.0.33.post1; (("linux" in sys_platform or sys_platform == "win32") and (platform_machine == "AMD64" or platform_machine == "x86_64")) and extra == "cu126onlytorch290"
Provides-Extra: cu128onlytorch290
Requires-Dist: xformers==0.0.33.post1; (("linux" in sys_platform or sys_platform == "win32") and (platform_machine == "AMD64" or platform_machine == "x86_64")) and extra == "cu128onlytorch290"
Provides-Extra: cu130onlytorch290
Requires-Dist: xformers==0.0.33.post1; (("linux" in sys_platform or sys_platform == "win32") and (platform_machine == "AMD64" or platform_machine == "x86_64")) and extra == "cu130onlytorch290"
Provides-Extra: cu126onlytorch291
Requires-Dist: xformers==0.0.33.post2; (("linux" in sys_platform or sys_platform == "win32") and (platform_machine == "AMD64" or platform_machine == "x86_64")) and extra == "cu126onlytorch291"
Provides-Extra: cu128onlytorch291
Requires-Dist: xformers==0.0.33.post2; (("linux" in sys_platform or sys_platform == "win32") and (platform_machine == "AMD64" or platform_machine == "x86_64")) and extra == "cu128onlytorch291"
Provides-Extra: cu130onlytorch291
Requires-Dist: xformers==0.0.33.post2; (("linux" in sys_platform or sys_platform == "win32") and (platform_machine == "AMD64" or platform_machine == "x86_64")) and extra == "cu130onlytorch291"
Provides-Extra: cu118
Requires-Dist: unsloth[huggingface]; extra == "cu118"
Requires-Dist: bitsandbytes!=0.46.0,!=0.48.0,>=0.45.5; extra == "cu118"
Requires-Dist: unsloth[cu118only]; extra == "cu118"
Provides-Extra: cu121
Requires-Dist: unsloth[huggingface]; extra == "cu121"
Requires-Dist: bitsandbytes!=0.46.0,!=0.48.0,>=0.45.5; extra == "cu121"
Requires-Dist: unsloth[cu121only]; extra == "cu121"
Provides-Extra: cu118-torch211
Requires-Dist: unsloth[huggingface]; extra == "cu118-torch211"
Requires-Dist: bitsandbytes!=0.46.0,!=0.48.0,>=0.45.5; extra == "cu118-torch211"
Requires-Dist: unsloth[cu118onlytorch211]; extra == "cu118-torch211"
Provides-Extra: cu121-torch211
Requires-Dist: unsloth[huggingface]; extra == "cu121-torch211"
Requires-Dist: bitsandbytes!=0.46.0,!=0.48.0,>=0.45.5; extra == "cu121-torch211"
Requires-Dist: unsloth[cu121onlytorch211]; extra == "cu121-torch211"
Provides-Extra: cu118-torch212
Requires-Dist: unsloth[huggingface]; extra == "cu118-torch212"
Requires-Dist: bitsandbytes!=0.46.0,!=0.48.0,>=0.45.5; extra == "cu118-torch212"
Requires-Dist: unsloth[cu118onlytorch212]; extra == "cu118-torch212"
Provides-Extra: cu121-torch212
Requires-Dist: unsloth[huggingface]; extra == "cu121-torch212"
Requires-Dist: bitsandbytes!=0.46.0,!=0.48.0,>=0.45.5; extra == "cu121-torch212"
Requires-Dist: unsloth[cu121onlytorch212]; extra == "cu121-torch212"
Provides-Extra: cu118-torch220
Requires-Dist: unsloth[huggingface]; extra == "cu118-torch220"
Requires-Dist: bitsandbytes!=0.46.0,!=0.48.0,>=0.45.5; extra == "cu118-torch220"
Requires-Dist: unsloth[cu118onlytorch220]; extra == "cu118-torch220"
Provides-Extra: cu121-torch220
Requires-Dist: unsloth[huggingface]; extra == "cu121-torch220"
Requires-Dist: bitsandbytes!=0.46.0,!=0.48.0,>=0.45.5; extra == "cu121-torch220"
Requires-Dist: unsloth[cu121onlytorch220]; extra == "cu121-torch220"
Provides-Extra: cu118-torch230
Requires-Dist: unsloth[huggingface]; extra == "cu118-torch230"
Requires-Dist: bitsandbytes!=0.46.0,!=0.48.0,>=0.45.5; extra == "cu118-torch230"
Requires-Dist: unsloth[cu118onlytorch230]; extra == "cu118-torch230"
Provides-Extra: cu121-torch230
Requires-Dist: unsloth[huggingface]; extra == "cu121-torch230"
Requires-Dist: bitsandbytes!=0.46.0,!=0.48.0,>=0.45.5; extra == "cu121-torch230"
Requires-Dist: unsloth[cu121onlytorch230]; extra == "cu121-torch230"
Provides-Extra: cu118-torch240
Requires-Dist: unsloth[huggingface]; extra == "cu118-torch240"
Requires-Dist: bitsandbytes!=0.46.0,!=0.48.0,>=0.45.5; extra == "cu118-torch240"
Requires-Dist: unsloth[cu118onlytorch240]; extra == "cu118-torch240"
Provides-Extra: cu121-torch240
Requires-Dist: unsloth[huggingface]; extra == "cu121-torch240"
Requires-Dist: bitsandbytes!=0.46.0,!=0.48.0,>=0.45.5; extra == "cu121-torch240"
Requires-Dist: unsloth[cu121onlytorch240]; extra == "cu121-torch240"
Provides-Extra: cu124-torch240
Requires-Dist: unsloth[huggingface]; extra == "cu124-torch240"
Requires-Dist: bitsandbytes!=0.46.0,!=0.48.0,>=0.45.5; extra == "cu124-torch240"
Requires-Dist: unsloth[cu124onlytorch240]; extra == "cu124-torch240"
Provides-Extra: cu118-torch250
Requires-Dist: unsloth[huggingface]; extra == "cu118-torch250"
Requires-Dist: bitsandbytes!=0.46.0,!=0.48.0,>=0.45.5; extra == "cu118-torch250"
Requires-Dist: unsloth[cu118onlytorch250]; extra == "cu118-torch250"
Provides-Extra: cu121-torch250
Requires-Dist: unsloth[huggingface]; extra == "cu121-torch250"
Requires-Dist: bitsandbytes!=0.46.0,!=0.48.0,>=0.45.5; extra == "cu121-torch250"
Requires-Dist: unsloth[cu121onlytorch250]; extra == "cu121-torch250"
Provides-Extra: cu124-torch250
Requires-Dist: unsloth[huggingface]; extra == "cu124-torch250"
Requires-Dist: bitsandbytes!=0.46.0,!=0.48.0,>=0.45.5; extra == "cu124-torch250"
Requires-Dist: unsloth[cu124onlytorch250]; extra == "cu124-torch250"
Provides-Extra: cu118-torch251
Requires-Dist: unsloth[huggingface]; extra == "cu118-torch251"
Requires-Dist: bitsandbytes!=0.46.0,!=0.48.0,>=0.45.5; extra == "cu118-torch251"
Requires-Dist: unsloth[cu118onlytorch251]; extra == "cu118-torch251"
Provides-Extra: cu121-torch251
Requires-Dist: unsloth[huggingface]; extra == "cu121-torch251"
Requires-Dist: bitsandbytes!=0.46.0,!=0.48.0,>=0.45.5; extra == "cu121-torch251"
Requires-Dist: unsloth[cu121onlytorch251]; extra == "cu121-torch251"
Provides-Extra: cu124-torch251
Requires-Dist: unsloth[huggingface]; extra == "cu124-torch251"
Requires-Dist: bitsandbytes!=0.46.0,!=0.48.0,>=0.45.5; extra == "cu124-torch251"
Requires-Dist: unsloth[cu124onlytorch251]; extra == "cu124-torch251"
Provides-Extra: cu118-torch260
Requires-Dist: unsloth[huggingface]; extra == "cu118-torch260"
Requires-Dist: bitsandbytes>=0.45.1; extra == "cu118-torch260"
Requires-Dist: unsloth[cu118onlytorch260]; extra == "cu118-torch260"
Provides-Extra: cu124-torch260
Requires-Dist: unsloth[huggingface]; extra == "cu124-torch260"
Requires-Dist: bitsandbytes>=0.45.1; extra == "cu124-torch260"
Requires-Dist: unsloth[cu124onlytorch260]; extra == "cu124-torch260"
Provides-Extra: cu126-torch260
Requires-Dist: unsloth[huggingface]; extra == "cu126-torch260"
Requires-Dist: bitsandbytes>=0.45.1; extra == "cu126-torch260"
Requires-Dist: unsloth[cu126onlytorch260]; extra == "cu126-torch260"
Provides-Extra: cu118-torch270
Requires-Dist: unsloth[huggingface]; extra == "cu118-torch270"
Requires-Dist: bitsandbytes!=0.46.0,!=0.48.0,>=0.45.5; extra == "cu118-torch270"
Requires-Dist: unsloth[cu118onlytorch270]; extra == "cu118-torch270"
Provides-Extra: cu126-torch270
Requires-Dist: unsloth[huggingface]; extra == "cu126-torch270"
Requires-Dist: bitsandbytes!=0.46.0,!=0.48.0,>=0.45.5; extra == "cu126-torch270"
Requires-Dist: unsloth[cu126onlytorch270]; extra == "cu126-torch270"
Provides-Extra: cu128-torch270
Requires-Dist: unsloth[huggingface]; extra == "cu128-torch270"
Requires-Dist: bitsandbytes!=0.46.0,!=0.48.0,>=0.45.5; extra == "cu128-torch270"
Requires-Dist: unsloth[cu128onlytorch270]; extra == "cu128-torch270"
Provides-Extra: cu118-torch271
Requires-Dist: unsloth[huggingface]; extra == "cu118-torch271"
Requires-Dist: bitsandbytes!=0.46.0,!=0.48.0,>=0.45.5; extra == "cu118-torch271"
Requires-Dist: unsloth[cu118onlytorch271]; extra == "cu118-torch271"
Provides-Extra: cu126-torch271
Requires-Dist: unsloth[huggingface]; extra == "cu126-torch271"
Requires-Dist: bitsandbytes!=0.46.0,!=0.48.0,>=0.45.5; extra == "cu126-torch271"
Requires-Dist: unsloth[cu126onlytorch271]; extra == "cu126-torch271"
Provides-Extra: cu128-torch271
Requires-Dist: unsloth[huggingface]; extra == "cu128-torch271"
Requires-Dist: bitsandbytes!=0.46.0,!=0.48.0,>=0.45.5; extra == "cu128-torch271"
Requires-Dist: unsloth[cu128onlytorch271]; extra == "cu128-torch271"
Provides-Extra: cu118-torch280
Requires-Dist: unsloth[huggingface]; extra == "cu118-torch280"
Requires-Dist: bitsandbytes!=0.46.0,!=0.48.0,>=0.45.5; extra == "cu118-torch280"
Requires-Dist: unsloth[cu118onlytorch280]; extra == "cu118-torch280"
Provides-Extra: cu126-torch280
Requires-Dist: unsloth[huggingface]; extra == "cu126-torch280"
Requires-Dist: bitsandbytes!=0.46.0,!=0.48.0,>=0.45.5; extra == "cu126-torch280"
Requires-Dist: unsloth[cu126onlytorch280]; extra == "cu126-torch280"
Provides-Extra: cu128-torch280
Requires-Dist: unsloth[huggingface]; extra == "cu128-torch280"
Requires-Dist: bitsandbytes!=0.46.0,!=0.48.0,>=0.45.5; extra == "cu128-torch280"
Requires-Dist: unsloth[cu128onlytorch280]; extra == "cu128-torch280"
Provides-Extra: cu130-torch280
Requires-Dist: unsloth[huggingface]; extra == "cu130-torch280"
Requires-Dist: bitsandbytes!=0.46.0,!=0.48.0,>=0.45.5; extra == "cu130-torch280"
Requires-Dist: unsloth[cu130onlytorch280]; extra == "cu130-torch280"
Provides-Extra: cu126-torch290
Requires-Dist: unsloth[huggingface]; extra == "cu126-torch290"
Requires-Dist: bitsandbytes!=0.46.0,!=0.48.0,>=0.45.5; extra == "cu126-torch290"
Requires-Dist: unsloth[cu126onlytorch290]; extra == "cu126-torch290"
Provides-Extra: cu128-torch290
Requires-Dist: unsloth[huggingface]; extra == "cu128-torch290"
Requires-Dist: bitsandbytes!=0.46.0,!=0.48.0,>=0.45.5; extra == "cu128-torch290"
Requires-Dist: unsloth[cu128onlytorch290]; extra == "cu128-torch290"
Provides-Extra: cu130-torch290
Requires-Dist: unsloth[huggingface]; extra == "cu130-torch290"
Requires-Dist: bitsandbytes!=0.46.0,!=0.48.0,>=0.45.5; extra == "cu130-torch290"
Requires-Dist: unsloth[cu130onlytorch290]; extra == "cu130-torch290"
Provides-Extra: cu126-torch291
Requires-Dist: unsloth[huggingface]; extra == "cu126-torch291"
Requires-Dist: bitsandbytes!=0.46.0,!=0.48.0,>=0.45.5; extra == "cu126-torch291"
Requires-Dist: unsloth[cu126onlytorch291]; extra == "cu126-torch291"
Provides-Extra: cu128-torch291
Requires-Dist: unsloth[huggingface]; extra == "cu128-torch291"
Requires-Dist: bitsandbytes!=0.46.0,!=0.48.0,>=0.45.5; extra == "cu128-torch291"
Requires-Dist: unsloth[cu128onlytorch291]; extra == "cu128-torch291"
Provides-Extra: cu130-torch291
Requires-Dist: unsloth[huggingface]; extra == "cu130-torch291"
Requires-Dist: bitsandbytes!=0.46.0,!=0.48.0,>=0.45.5; extra == "cu130-torch291"
Requires-Dist: unsloth[cu130onlytorch291]; extra == "cu130-torch291"
Provides-Extra: kaggle
Requires-Dist: unsloth[huggingface]; extra == "kaggle"
Provides-Extra: kaggle-new
Requires-Dist: unsloth[huggingface]; extra == "kaggle-new"
Requires-Dist: bitsandbytes!=0.46.0,!=0.48.0,>=0.45.5; extra == "kaggle-new"
Provides-Extra: conda
Requires-Dist: unsloth[huggingface]; extra == "conda"
Provides-Extra: colab-torch211
Requires-Dist: unsloth[huggingface]; extra == "colab-torch211"
Requires-Dist: bitsandbytes!=0.46.0,!=0.48.0,>=0.45.5; extra == "colab-torch211"
Requires-Dist: unsloth[cu121onlytorch211]; extra == "colab-torch211"
Provides-Extra: flashattention
Requires-Dist: packaging; "linux" in sys_platform and extra == "flashattention"
Requires-Dist: ninja; "linux" in sys_platform and extra == "flashattention"
Requires-Dist: flash-attn>=2.6.3; "linux" in sys_platform and extra == "flashattention"
Provides-Extra: colab-ampere-torch211
Requires-Dist: unsloth[huggingface]; extra == "colab-ampere-torch211"
Requires-Dist: bitsandbytes!=0.46.0,!=0.48.0,>=0.45.5; extra == "colab-ampere-torch211"
Requires-Dist: unsloth[cu121onlytorch211]; extra == "colab-ampere-torch211"
Requires-Dist: unsloth[flashattention]; extra == "colab-ampere-torch211"
Provides-Extra: colab-torch220
Requires-Dist: unsloth[huggingface]; extra == "colab-torch220"
Requires-Dist: bitsandbytes!=0.46.0,!=0.48.0,>=0.45.5; extra == "colab-torch220"
Requires-Dist: unsloth[cu121onlytorch220]; extra == "colab-torch220"
Provides-Extra: colab-ampere-torch220
Requires-Dist: unsloth[huggingface]; extra == "colab-ampere-torch220"
Requires-Dist: bitsandbytes!=0.46.0,!=0.48.0,>=0.45.5; extra == "colab-ampere-torch220"
Requires-Dist: unsloth[cu121onlytorch220]; extra == "colab-ampere-torch220"
Requires-Dist: unsloth[flashattention]; extra == "colab-ampere-torch220"
Provides-Extra: colab-new
Requires-Dist: unsloth_zoo>=2026.1.2; extra == "colab-new"
Requires-Dist: packaging; extra == "colab-new"
Requires-Dist: tyro; extra == "colab-new"
Requires-Dist: transformers!=4.52.0,!=4.52.1,!=4.52.2,!=4.52.3,!=4.53.0,!=4.54.0,!=4.55.0,!=4.55.1,!=4.57.0,<=4.57.3,>=4.51.3; extra == "colab-new"
Requires-Dist: datasets!=4.0.*,!=4.1.0,<4.4.0,>=3.4.1; extra == "colab-new"
Requires-Dist: sentencepiece>=0.2.0; extra == "colab-new"
Requires-Dist: tqdm; extra == "colab-new"
Requires-Dist: psutil; extra == "colab-new"
Requires-Dist: wheel>=0.42.0; extra == "colab-new"
Requires-Dist: numpy; extra == "colab-new"
Requires-Dist: protobuf; extra == "colab-new"
Requires-Dist: huggingface_hub>=0.34.0; extra == "colab-new"
Requires-Dist: hf_transfer; extra == "colab-new"
Requires-Dist: bitsandbytes!=0.46.0,!=0.48.0,>=0.45.5; extra == "colab-new"
Requires-Dist: unsloth[triton]; extra == "colab-new"
Provides-Extra: colab-no-deps
Requires-Dist: accelerate>=0.34.1; extra == "colab-no-deps"
Requires-Dist: trl!=0.19.0,<=0.24.0,>=0.18.2; extra == "colab-no-deps"
Requires-Dist: peft>=0.7.1; extra == "colab-no-deps"
Requires-Dist: xformers<0.0.27; extra == "colab-no-deps"
Requires-Dist: bitsandbytes!=0.46.0,!=0.48.0,>=0.45.5; extra == "colab-no-deps"
Requires-Dist: protobuf; extra == "colab-no-deps"
Provides-Extra: colab
Requires-Dist: unsloth[cu121]; extra == "colab"
Provides-Extra: colab-ampere
Requires-Dist: unsloth[colab-ampere-torch220]; extra == "colab-ampere"
Requires-Dist: unsloth[flashattention]; extra == "colab-ampere"
Provides-Extra: cu118-ampere
Requires-Dist: unsloth[huggingface]; extra == "cu118-ampere"
Requires-Dist: bitsandbytes!=0.46.0,!=0.48.0,>=0.45.5; extra == "cu118-ampere"
Requires-Dist: unsloth[cu118only]; extra == "cu118-ampere"
Requires-Dist: unsloth[flashattention]; extra == "cu118-ampere"
Provides-Extra: cu121-ampere
Requires-Dist: unsloth[huggingface]; extra == "cu121-ampere"
Requires-Dist: bitsandbytes!=0.46.0,!=0.48.0,>=0.45.5; extra == "cu121-ampere"
Requires-Dist: unsloth[cu121only]; extra == "cu121-ampere"
Requires-Dist: unsloth[flashattention]; extra == "cu121-ampere"
Provides-Extra: cu118-ampere-torch211
Requires-Dist: unsloth[huggingface]; extra == "cu118-ampere-torch211"
Requires-Dist: bitsandbytes!=0.46.0,!=0.48.0,>=0.45.5; extra == "cu118-ampere-torch211"
Requires-Dist: unsloth[cu118onlytorch211]; extra == "cu118-ampere-torch211"
Requires-Dist: unsloth[flashattention]; extra == "cu118-ampere-torch211"
Provides-Extra: cu121-ampere-torch211
Requires-Dist: unsloth[huggingface]; extra == "cu121-ampere-torch211"
Requires-Dist: bitsandbytes!=0.46.0,!=0.48.0,>=0.45.5; extra == "cu121-ampere-torch211"
Requires-Dist: unsloth[cu121onlytorch211]; extra == "cu121-ampere-torch211"
Requires-Dist: unsloth[flashattention]; extra == "cu121-ampere-torch211"
Provides-Extra: cu118-ampere-torch220
Requires-Dist: unsloth[huggingface]; extra == "cu118-ampere-torch220"
Requires-Dist: bitsandbytes!=0.46.0,!=0.48.0,>=0.45.5; extra == "cu118-ampere-torch220"
Requires-Dist: unsloth[cu118onlytorch220]; extra == "cu118-ampere-torch220"
Requires-Dist: unsloth[flashattention]; extra == "cu118-ampere-torch220"
Provides-Extra: cu121-ampere-torch220
Requires-Dist: unsloth[huggingface]; extra == "cu121-ampere-torch220"
Requires-Dist: bitsandbytes!=0.46.0,!=0.48.0,>=0.45.5; extra == "cu121-ampere-torch220"
Requires-Dist: unsloth[cu121onlytorch220]; extra == "cu121-ampere-torch220"
Requires-Dist: unsloth[flashattention]; extra == "cu121-ampere-torch220"
Provides-Extra: cu118-ampere-torch230
Requires-Dist: unsloth[huggingface]; extra == "cu118-ampere-torch230"
Requires-Dist: bitsandbytes!=0.46.0,!=0.48.0,>=0.45.5; extra == "cu118-ampere-torch230"
Requires-Dist: unsloth[cu118onlytorch230]; extra == "cu118-ampere-torch230"
Requires-Dist: unsloth[flashattention]; extra == "cu118-ampere-torch230"
Provides-Extra: cu121-ampere-torch230
Requires-Dist: unsloth[huggingface]; extra == "cu121-ampere-torch230"
Requires-Dist: bitsandbytes!=0.46.0,!=0.48.0,>=0.45.5; extra == "cu121-ampere-torch230"
Requires-Dist: unsloth[cu121onlytorch230]; extra == "cu121-ampere-torch230"
Requires-Dist: unsloth[flashattention]; extra == "cu121-ampere-torch230"
Provides-Extra: cu118-ampere-torch240
Requires-Dist: unsloth[huggingface]; extra == "cu118-ampere-torch240"
Requires-Dist: bitsandbytes!=0.46.0,!=0.48.0,>=0.45.5; extra == "cu118-ampere-torch240"
Requires-Dist: unsloth[cu118onlytorch240]; extra == "cu118-ampere-torch240"
Requires-Dist: unsloth[flashattention]; extra == "cu118-ampere-torch240"
Provides-Extra: cu121-ampere-torch240
Requires-Dist: unsloth[huggingface]; extra == "cu121-ampere-torch240"
Requires-Dist: bitsandbytes!=0.46.0,!=0.48.0,>=0.45.5; extra == "cu121-ampere-torch240"
Requires-Dist: unsloth[cu121onlytorch240]; extra == "cu121-ampere-torch240"
Requires-Dist: unsloth[flashattention]; extra == "cu121-ampere-torch240"
Provides-Extra: cu124-ampere-torch240
Requires-Dist: unsloth[huggingface]; extra == "cu124-ampere-torch240"
Requires-Dist: bitsandbytes!=0.46.0,!=0.48.0,>=0.45.5; extra == "cu124-ampere-torch240"
Requires-Dist: unsloth[cu124onlytorch240]; extra == "cu124-ampere-torch240"
Requires-Dist: unsloth[flashattention]; extra == "cu124-ampere-torch240"
Provides-Extra: cu118-ampere-torch250
Requires-Dist: unsloth[huggingface]; extra == "cu118-ampere-torch250"
Requires-Dist: bitsandbytes!=0.46.0,!=0.48.0,>=0.45.5; extra == "cu118-ampere-torch250"
Requires-Dist: unsloth[cu118onlytorch250]; extra == "cu118-ampere-torch250"
Requires-Dist: unsloth[flashattention]; extra == "cu118-ampere-torch250"
Provides-Extra: cu121-ampere-torch250
Requires-Dist: unsloth[huggingface]; extra == "cu121-ampere-torch250"
Requires-Dist: bitsandbytes!=0.46.0,!=0.48.0,>=0.45.5; extra == "cu121-ampere-torch250"
Requires-Dist: unsloth[cu121onlytorch250]; extra == "cu121-ampere-torch250"
Requires-Dist: unsloth[flashattention]; extra == "cu121-ampere-torch250"
Provides-Extra: cu124-ampere-torch250
Requires-Dist: unsloth[huggingface]; extra == "cu124-ampere-torch250"
Requires-Dist: bitsandbytes!=0.46.0,!=0.48.0,>=0.45.5; extra == "cu124-ampere-torch250"
Requires-Dist: unsloth[cu124onlytorch250]; extra == "cu124-ampere-torch250"
Requires-Dist: unsloth[flashattention]; extra == "cu124-ampere-torch250"
Provides-Extra: cu118-ampere-torch251
Requires-Dist: unsloth[huggingface]; extra == "cu118-ampere-torch251"
Requires-Dist: bitsandbytes!=0.46.0,!=0.48.0,>=0.45.5; extra == "cu118-ampere-torch251"
Requires-Dist: unsloth[cu118onlytorch251]; extra == "cu118-ampere-torch251"
Requires-Dist: unsloth[flashattention]; extra == "cu118-ampere-torch251"
Provides-Extra: cu121-ampere-torch251
Requires-Dist: unsloth[huggingface]; extra == "cu121-ampere-torch251"
Requires-Dist: bitsandbytes!=0.46.0,!=0.48.0,>=0.45.5; extra == "cu121-ampere-torch251"
Requires-Dist: unsloth[cu121onlytorch251]; extra == "cu121-ampere-torch251"
Requires-Dist: unsloth[flashattention]; extra == "cu121-ampere-torch251"
Provides-Extra: cu124-ampere-torch251
Requires-Dist: unsloth[huggingface]; extra == "cu124-ampere-torch251"
Requires-Dist: bitsandbytes!=0.46.0,!=0.48.0,>=0.45.5; extra == "cu124-ampere-torch251"
Requires-Dist: unsloth[cu124onlytorch251]; extra == "cu124-ampere-torch251"
Requires-Dist: unsloth[flashattention]; extra == "cu124-ampere-torch251"
Provides-Extra: cu118-ampere-torch260
Requires-Dist: unsloth[huggingface]; extra == "cu118-ampere-torch260"
Requires-Dist: bitsandbytes>=0.45.1; extra == "cu118-ampere-torch260"
Requires-Dist: unsloth[cu118onlytorch260]; extra == "cu118-ampere-torch260"
Requires-Dist: unsloth[flashattention]; extra == "cu118-ampere-torch260"
Provides-Extra: cu124-ampere-torch260
Requires-Dist: unsloth[huggingface]; extra == "cu124-ampere-torch260"
Requires-Dist: bitsandbytes>=0.45.1; extra == "cu124-ampere-torch260"
Requires-Dist: unsloth[cu124onlytorch260]; extra == "cu124-ampere-torch260"
Requires-Dist: unsloth[flashattention]; extra == "cu124-ampere-torch260"
Provides-Extra: cu126-ampere-torch260
Requires-Dist: unsloth[huggingface]; extra == "cu126-ampere-torch260"
Requires-Dist: bitsandbytes>=0.45.1; extra == "cu126-ampere-torch260"
Requires-Dist: unsloth[cu126onlytorch260]; extra == "cu126-ampere-torch260"
Requires-Dist: unsloth[flashattention]; extra == "cu126-ampere-torch260"
Provides-Extra: cu118-ampere-torch270
Requires-Dist: unsloth[huggingface]; extra == "cu118-ampere-torch270"
Requires-Dist: bitsandbytes!=0.46.0,!=0.48.0,>=0.45.5; extra == "cu118-ampere-torch270"
Requires-Dist: unsloth[cu118onlytorch270]; extra == "cu118-ampere-torch270"
Requires-Dist: unsloth[flashattention]; extra == "cu118-ampere-torch270"
Provides-Extra: cu126-ampere-torch270
Requires-Dist: unsloth[huggingface]; extra == "cu126-ampere-torch270"
Requires-Dist: bitsandbytes!=0.46.0,!=0.48.0,>=0.45.5; extra == "cu126-ampere-torch270"
Requires-Dist: unsloth[cu126onlytorch270]; extra == "cu126-ampere-torch270"
Requires-Dist: unsloth[flashattention]; extra == "cu126-ampere-torch270"
Provides-Extra: cu128-ampere-torch270
Requires-Dist: unsloth[huggingface]; extra == "cu128-ampere-torch270"
Requires-Dist: bitsandbytes!=0.46.0,!=0.48.0,>=0.45.5; extra == "cu128-ampere-torch270"
Requires-Dist: unsloth[cu128onlytorch270]; extra == "cu128-ampere-torch270"
Requires-Dist: unsloth[flashattention]; extra == "cu128-ampere-torch270"
Provides-Extra: cu118-ampere-torch271
Requires-Dist: unsloth[huggingface]; extra == "cu118-ampere-torch271"
Requires-Dist: bitsandbytes!=0.46.0,!=0.48.0,>=0.45.5; extra == "cu118-ampere-torch271"
Requires-Dist: unsloth[cu118onlytorch271]; extra == "cu118-ampere-torch271"
Requires-Dist: unsloth[flashattention]; extra == "cu118-ampere-torch271"
Provides-Extra: cu126-ampere-torch271
Requires-Dist: unsloth[huggingface]; extra == "cu126-ampere-torch271"
Requires-Dist: bitsandbytes!=0.46.0,!=0.48.0,>=0.45.5; extra == "cu126-ampere-torch271"
Requires-Dist: unsloth[cu126onlytorch271]; extra == "cu126-ampere-torch271"
Requires-Dist: unsloth[flashattention]; extra == "cu126-ampere-torch271"
Provides-Extra: cu128-ampere-torch271
Requires-Dist: unsloth[huggingface]; extra == "cu128-ampere-torch271"
Requires-Dist: bitsandbytes!=0.46.0,!=0.48.0,>=0.45.5; extra == "cu128-ampere-torch271"
Requires-Dist: unsloth[cu128onlytorch271]; extra == "cu128-ampere-torch271"
Requires-Dist: unsloth[flashattention]; extra == "cu128-ampere-torch271"
Provides-Extra: cu118-ampere-torch280
Requires-Dist: unsloth[huggingface]; extra == "cu118-ampere-torch280"
Requires-Dist: bitsandbytes!=0.46.0,!=0.48.0,>=0.45.5; extra == "cu118-ampere-torch280"
Requires-Dist: unsloth[cu118onlytorch280]; extra == "cu118-ampere-torch280"
Requires-Dist: unsloth[flashattention]; extra == "cu118-ampere-torch280"
Provides-Extra: cu126-ampere-torch280
Requires-Dist: unsloth[huggingface]; extra == "cu126-ampere-torch280"
Requires-Dist: bitsandbytes!=0.46.0,!=0.48.0,>=0.45.5; extra == "cu126-ampere-torch280"
Requires-Dist: unsloth[cu126onlytorch280]; extra == "cu126-ampere-torch280"
Requires-Dist: unsloth[flashattention]; extra == "cu126-ampere-torch280"
Provides-Extra: cu128-ampere-torch280
Requires-Dist: unsloth[huggingface]; extra == "cu128-ampere-torch280"
Requires-Dist: bitsandbytes!=0.46.0,!=0.48.0,>=0.45.5; extra == "cu128-ampere-torch280"
Requires-Dist: unsloth[cu128onlytorch280]; extra == "cu128-ampere-torch280"
Requires-Dist: unsloth[flashattention]; extra == "cu128-ampere-torch280"
Provides-Extra: cu130-ampere-torch280
Requires-Dist: unsloth[huggingface]; extra == "cu130-ampere-torch280"
Requires-Dist: bitsandbytes!=0.46.0,!=0.48.0,>=0.45.5; extra == "cu130-ampere-torch280"
Requires-Dist: unsloth[cu130onlytorch280]; extra == "cu130-ampere-torch280"
Provides-Extra: cu126-ampere-torch290
Requires-Dist: unsloth[huggingface]; extra == "cu126-ampere-torch290"
Requires-Dist: bitsandbytes!=0.46.0,!=0.48.0,>=0.45.5; extra == "cu126-ampere-torch290"
Requires-Dist: unsloth[cu126onlytorch290]; extra == "cu126-ampere-torch290"
Provides-Extra: cu128-ampere-torch290
Requires-Dist: unsloth[huggingface]; extra == "cu128-ampere-torch290"
Requires-Dist: bitsandbytes!=0.46.0,!=0.48.0,>=0.45.5; extra == "cu128-ampere-torch290"
Requires-Dist: unsloth[cu128onlytorch290]; extra == "cu128-ampere-torch290"
Provides-Extra: cu130-ampere-torch290
Requires-Dist: unsloth[huggingface]; extra == "cu130-ampere-torch290"
Requires-Dist: bitsandbytes!=0.46.0,!=0.48.0,>=0.45.5; extra == "cu130-ampere-torch290"
Requires-Dist: unsloth[cu130onlytorch290]; extra == "cu130-ampere-torch290"
Provides-Extra: cu126-ampere-torch291
Requires-Dist: unsloth[huggingface]; extra == "cu126-ampere-torch291"
Requires-Dist: bitsandbytes!=0.46.0,!=0.48.0,>=0.45.5; extra == "cu126-ampere-torch291"
Requires-Dist: unsloth[cu126onlytorch291]; extra == "cu126-ampere-torch291"
Provides-Extra: cu128-ampere-torch291
Requires-Dist: unsloth[huggingface]; extra == "cu128-ampere-torch291"
Requires-Dist: bitsandbytes!=0.46.0,!=0.48.0,>=0.45.5; extra == "cu128-ampere-torch291"
Requires-Dist: unsloth[cu128onlytorch291]; extra == "cu128-ampere-torch291"
Provides-Extra: cu130-ampere-torch291
Requires-Dist: unsloth[huggingface]; extra == "cu130-ampere-torch291"
Requires-Dist: bitsandbytes!=0.46.0,!=0.48.0,>=0.45.5; extra == "cu130-ampere-torch291"
Requires-Dist: unsloth[cu130onlytorch291]; extra == "cu130-ampere-torch291"
Dynamic: license-file
